pyinjector/__init__.py
pyinjector/__main__.py
pyinjector/api.py
pyinjector/injector.cp310-win32.pyd
pyinjector-1.3.0.dist-info/LICENSE
pyinjector-1.3.0.dist-info/METADATA
pyinjector-1.3.0.dist-info/WHEEL
pyinjector-1.3.0.dist-info/entry_points.txt
pyinjector-1.3.0.dist-info/top_level.txt
pyinjector-1.3.0.dist-info/RECORD
