Metadata-Version: 2.1
Name: pyinjector
Version: 1.3.0
Summary: A tool/library allowing dynamic library injection into running processes
Home-page: https://github.com/kmaork/pyinjector
Author: Maor Kleinberger
Author-email: kmaork@gmail.com
Keywords: injection dll so library
Classifier: Intended Audience :: Developers
Classifier: License :: OSI Approved :: MIT License
Classifier: Programming Language :: Python :: 3
Classifier: Programming Language :: Python :: 3 :: Only
Classifier: Programming Language :: Python :: 3.7
Classifier: Programming Language :: Python :: 3.8
Classifier: Programming Language :: Python :: 3.9
Classifier: Programming Language :: Python :: 3.10
Classifier: Programming Language :: Python :: 3.11
Classifier: Topic :: Software Development :: Libraries :: Python Modules
Requires-Python: >=3.7
License-File: LICENSE
